opensearch_logger/__init__.py
opensearch_logger/handlers.py
opensearch_logger/serializers.py
opensearch_logger/version.py
opensearch_logger-1.3.1.dist-info/METADATA
opensearch_logger-1.3.1.dist-info/WHEEL
opensearch_logger-1.3.1.dist-info/licenses/LICENSE.md
opensearch_logger-1.3.1.dist-info/RECORD
