Metadata-Version: 2.4
Name: opensearch-logger
Version: 1.3.1
Summary: OpenSearch logging handler
Project-URL: documentation, https://github.com/vduseev/opensearch-logger
Project-URL: homepage, https://github.com/vduseev/opensearch-logger
Project-URL: repository, https://github.com/vduseev/opensearch-logger
Author-email: vduseev <vagiz@duseev.com>, IMInterne <equipe_interne@innovmetric.com>
Maintainer-email: vduseev <vagiz@duseev.com>
License: Copyright 2021-2025 Vagiz Duseev
License-File: LICENSE.md
Keywords: handler,logger,logging,opensearch
Classifier: Development Status :: 5 - Production/Stable
Classifier: Intended Audience :: Developers
Classifier: License :: OSI Approved :: Apache Software License
Classifier: Programming Language :: Python :: 3.9
Classifier: Programming Language :: Python :: 3.10
Classifier: Programming Language :: Python :: 3.11
Classifier: Programming Language :: Python :: 3.12
Classifier: Programming Language :: Python :: 3.13
Classifier: Topic :: Internet :: Log Analysis
Classifier: Topic :: Software Development :: Libraries
Classifier: Topic :: System :: Logging
Requires-Python: >=3.9
Requires-Dist: opensearch-py
Provides-Extra: dev
Requires-Dist: mypy; extra == 'dev'
Requires-Dist: pytest; extra == 'dev'
Requires-Dist: pytest-cov; extra == 'dev'
Requires-Dist: pytest-mypy; extra == 'dev'
Requires-Dist: ruff; extra == 'dev'
